{
	"data": {
		"items": [
			{
				"comment": "ligula in lacus curabitur at ipsum ac tellus semper interdum",
				"ecmeActivityLog": "JUL 21, 2004@15:29:34",
				"initiatorofECMEActivity": "WILLETT,DONALD C",
				"rxReference": null
			},
			{
				"comment": "imperdiet nullam orci pede venenatis non sodales sed tincidunt eu felis fusce posuere felis sed lacus morbi sem mauris laoreet",
				"ecmeActivityLog": "JUL 21, 2004@15:29:41",
				"initiatorofECMEActivity": "KEAYSELL, ABIGALE",
				"rxReference": 0
			},
			{
				"comment": "in sagittis dui vel nisl duis ac nibh fusce lacus purus aliquet at",
				"ecmeActivityLog": "MAY 21, 2019@02:15:41",
				"initiatorofECMEActivity": "CONISBEE, GALINA",
				"rxReference": 1
			},
			{
				"comment": "montes nascetur ridiculus mus etiam vel augue vestibulum rutrum rutrum neque aenean auctor gravida sem praesent id massa",
				"ecmeActivityLog": "APR 24, 2004@10:11:41",
				"initiatorofECMEActivity": "LAPERE, OTHELLA",
				"rxReference": 2
			},
			{
				"comment": "vestibulum proin eu mi nulla ac enim in tempor turpis nec euismod scelerisque quam turpis adipiscing",
				"ecmeActivityLog": "OCT 15, 2014@15:29:41",
				"initiatorofECMEActivity": "LAPERE, OTHELLA",
				"rxReference": 3
			},
			{
				"comment": "nunc donec quis orci eget orci vehicula condimentum curabitur in libero ut massa volutpat convallis",
				"ecmeActivityLog": "FEB 21, 2018@16:09:41",
				"initiatorofECMEActivity": "FLANCINBAUM, CASPER",
				"rxReference": 4
			},
			{
				"comment": "curabitur in libero ut massa volutpat convallis morbi odio odio elementum eu",
				"ecmeActivityLog": "MAY 25, 2021@06:12:41",
				"initiatorofECMEActivity": "BRIGSTOCK, KELVIN",
				"rxReference": 5
			},
			{
				"comment": "ac neque duis bibendum morbi non quam nec dui luctus rutrum nulla tellus in sagittis dui vel nisl duis ac",
				"ecmeActivityLog": "SEP 11, 2015@11:39:41",
				"initiatorofECMEActivity": "ATYEO, MAY",
				"rxReference": 6
			},
			{
				"comment": "condimentum neque sapien placerat ante nulla justo aliquam quis turpis eget elit",
				"ecmeActivityLog": "AUG 3, 2004@02:23:41",
				"initiatorofECMEActivity": "ATYEO, MAY",
				"rxReference": 7
			},
			{
				"comment": "neque sapien placerat sagittis dui vel nisl duis elit",
				"ecmeActivityLog": "JUN 13, 2001@05:11:14",
				"initiatorofECMEActivity": "GRACE, JASMINE",
				"rxReference": 8
			}
		],
		"total items": 10,
		"updated": "20221109154644-0400"
	}
}
